html_meta_data_parse/__init__.py
html_meta_data_parse/util.py
html_meta_data_parse-0.0.32.dist-info/METADATA
html_meta_data_parse-0.0.32.dist-info/WHEEL
html_meta_data_parse-0.0.32.dist-info/top_level.txt
html_meta_data_parse-0.0.32.dist-info/RECORD
