Metadata-Version: 2.1
Name: html-meta-data-parse
Version: 0.0.32
Summary: Collects metadata from URL, or HTML content.
Home-page: https://github.com/ikp4success/html_meta_data_parse
Author: Immanuel George
Author-email: ikp4success@aol.com
License: MIT
Project-URL: Tracker, https://github.com/ikp4success/html_meta_data_parse/issues
Platform: UNKNOWN
Classifier: Intended Audience :: Developers
Classifier: License :: OSI Approved :: MIT License
Classifier: Programming Language :: Python :: 3.6
Classifier: Programming Language :: Python :: 3.7
Classifier: Programming Language :: Python :: 3.8
Requires-Python: >=3.6
Requires-Dist: beautifulsoup4 (>=4.9.3)
Requires-Dist: requests (>=2.22.0)
Requires-Dist: parsel (>=1.6.0)
